lightutils/__init__.py
lightutils/common/__init__.py
lightutils/common/chunk.py
lightutils/common/color.py
lightutils/common/file.py
lightutils/common/log.py
lightutils/common/string.py
lightutils/common/text_compare.py
lightutils/common/time_format.py
lightutils/common/variable.py
lightutils/io/__init__.py
lightutils/io/json_file.py
lightutils/io/notification.py
lightutils/io/yaml_file.py
lightutils/sys/__init__.py
lightutils/sys/cmd.py
lightutils/sys/path.py
lightutils/sys/port.py
lightUtils-0.1.18.dist-info/LICENSE
lightUtils-0.1.18.dist-info/METADATA
lightUtils-0.1.18.dist-info/WHEEL
lightUtils-0.1.18.dist-info/top_level.txt
lightUtils-0.1.18.dist-info/RECORD
