Metadata-Version: 2.1
Name: lightUtils
Version: 0.1.18
Summary: lightsmile's personal Python util libs
Home-page: https://github.com/smilelight/lightUtils
Author: lightsmile
Author-email: iamlightsmile@gmail.com
License: MIT
Platform: UNKNOWN
Classifier: Development Status :: 4 - Beta
Classifier: Operating System :: OS Independent
Classifier: Intended Audience :: Developers
Classifier: License :: OSI Approved :: BSD License
Classifier: Programming Language :: Python
Classifier: Programming Language :: Python :: 3
Classifier: Programming Language :: Python :: 3.4
Classifier: Programming Language :: Python :: 3.5
Classifier: Programming Language :: Python :: 3.6
Classifier: Programming Language :: Python :: 3.7
Classifier: Topic :: Software Development :: Libraries
License-File: LICENSE
Requires-Dist: requests
Requires-Dist: yagmail
Requires-Dist: PyYAML
Requires-Dist: tqdm
